LICENSE
MANIFEST.in
README.rst
setup.cfg
setup.py
girder_resource_path_tools.egg-info/PKG-INFO
girder_resource_path_tools.egg-info/SOURCES.txt
girder_resource_path_tools.egg-info/dependency_links.txt
girder_resource_path_tools.egg-info/entry_points.txt
girder_resource_path_tools.egg-info/not-zip-safe
girder_resource_path_tools.egg-info/requires.txt
girder_resource_path_tools.egg-info/top_level.txt
resource_path_tools/__init__.py