Metadata-Version: 2.1
Name: girder-resource-path-tools
Version: 0.0.0
Summary: Add resource path utility endpoints.
Home-page: https://github.com/girder/resource_path_tools
Author: Kitware, Inc.
Author-email: kitware@kitware.com
License: Apache Software License 2.0
Keywords: girder-plugin,resource_path_tools
Platform: UNKNOWN
Classifier: Development Status :: 2 - Pre-Alpha
Classifier: License :: OSI Approved :: Apache Software License
Classifier: Natural Language :: English
Classifier: Programming Language :: Python :: 2
Classifier: Programming Language :: Python :: 2.7
Classifier: Programming Language :: Python :: 3
Classifier: Programming Language :: Python :: 3.5
Classifier: Programming Language :: Python :: 3.6
Classifier: Programming Language :: Python :: 3.7
